hyperquant/__init__.py
hyperquant/api.py
hyperquant/clients/__init__.py
hyperquant/clients/binance.py
hyperquant/clients/bitmex.py
hyperquant/clients/singleton_helper.py
hyperquant/clients/utils.py
hyperquant/clients/tests/__init__.py
hyperquant/clients/tests/test_binance_rest.py
hyperquant/clients/tests/test_binance_ws.py
hyperquant/clients/tests/test_bitmex_rest.py
hyperquant/clients/tests/test_bitmex_ws.py
hyperquant/clients/tests/test_init.py
hyperquant/clients/tests/test_utils.py
hyperquant/clients/tests/utils.py
hyperquant/utils/__init__.py
hyperquant/utils/dict_util.py
hyperquant/utils/log_util.py
hyperquant/utils/math_util.py
hyperquant/utils/test_util.py
hyperquant/utils/time_util.py
hyperquant/utils/tests/__init__.py
hyperquant/utils/tests/test_dict_util.py
hyperquant/utils/tests/test_log_util.py
hyperquant/utils/tests/test_math_util.py
hyperquant/utils/tests/test_test_util.py
hyperquant/utils/tests/test_time_util.py
hyperquant_framework-0.1.dist-info/METADATA
hyperquant_framework-0.1.dist-info/WHEEL
hyperquant_framework-0.1.dist-info/top_level.txt
hyperquant_framework-0.1.dist-info/RECORD
